<?xml version="1.0" encoding="utf-8"?>
<annotation>
<folder>images</folder>
<filename>OC_paper_11page_15_IvbmyqA</filename>
<source>
<database>MyDatabase</database>
<annotation>COCO2017</annotation>
<image>flickr</image>
<flickrid>NULL</flickrid>
<annotator>user@ireadrx.ai</annotator>
</source>
<owner>
<flickrid>NULL</flickrid>
<name>Label Studio</name>
</owner>
<size>
<width>2125</width>
<height>2750</height>
<depth>3</depth>
</size>
<segmented>0</segmented>
<object>
<name>reactions</name>
<pose>Unspecified</pose>
<truncated>0</truncated>
<difficult>0</difficult>
<bndbox>
<xmin>248</xmin>
<ymin>2279</ymin>
<xmax>998</xmax>
<ymax>2668</ymax>
</bndbox>
</object>
<object>
<name>reactions</name>
<pose>Unspecified</pose>
<truncated>0</truncated>
<difficult>0</difficult>
<bndbox>
<xmin>1126</xmin>
<ymin>1923</ymin>
<xmax>1813</xmax>
<ymax>2191</ymax>
</bndbox>
</object>
<object>
<name>reactions</name>
<pose>Unspecified</pose>
<truncated>0</truncated>
<difficult>0</difficult>
<bndbox>
<xmin>294</xmin>
<ymin>1014</ymin>
<xmax>997</xmax>
<ymax>1406</ymax>
</bndbox>
</object>
<object>
<name>reactions</name>
<pose>Unspecified</pose>
<truncated>0</truncated>
<difficult>0</difficult>
<bndbox>
<xmin>1109</xmin>
<ymin>248</ymin>
<xmax>1869</xmax>
<ymax>546</ymax>
</bndbox>
</object>
</annotation>
