<?xml version="1.0" encoding="utf-8"?>
<annotation>
<folder>images</folder>
<filename>OC_paper_3page_60_xhzgT8x</filename>
<source>
<database>MyDatabase</database>
<annotation>COCO2017</annotation>
<image>flickr</image>
<flickrid>NULL</flickrid>
<annotator>user@ireadrx.ai</annotator>
</source>
<owner>
<flickrid>NULL</flickrid>
<name>Label Studio</name>
</owner>
<size>
<width>2134</width>
<height>2750</height>
<depth>3</depth>
</size>
<segmented>0</segmented>
<object>
<name>relevant-structures</name>
<pose>Unspecified</pose>
<truncated>0</truncated>
<difficult>0</difficult>
<bndbox>
<xmin>410</xmin>
<ymin>781</ymin>
<xmax>847</xmax>
<ymax>1050</ymax>
</bndbox>
</object>
<object>
<name>relevant-structures</name>
<pose>Unspecified</pose>
<truncated>0</truncated>
<difficult>0</difficult>
<bndbox>
<xmin>430</xmin>
<ymin>1075</ymin>
<xmax>864</xmax>
<ymax>1364</ymax>
</bndbox>
</object>
<object>
<name>relevant-structures</name>
<pose>Unspecified</pose>
<truncated>0</truncated>
<difficult>0</difficult>
<bndbox>
<xmin>424</xmin>
<ymin>1381</ymin>
<xmax>871</xmax>
<ymax>1637</ymax>
</bndbox>
</object>
<object>
<name>relevant-structures</name>
<pose>Unspecified</pose>
<truncated>0</truncated>
<difficult>0</difficult>
<bndbox>
<xmin>437</xmin>
<ymin>1647</ymin>
<xmax>857</xmax>
<ymax>1923</ymax>
</bndbox>
</object>
<object>
<name>relevant-structures</name>
<pose>Unspecified</pose>
<truncated>0</truncated>
<difficult>0</difficult>
<bndbox>
<xmin>400</xmin>
<ymin>1951</ymin>
<xmax>901</xmax>
<ymax>2227</ymax>
</bndbox>
</object>
<object>
<name>relevant-structures</name>
<pose>Unspecified</pose>
<truncated>0</truncated>
<difficult>0</difficult>
<bndbox>
<xmin>454</xmin>
<ymin>2244</ymin>
<xmax>861</xmax>
<ymax>2658</ymax>
</bndbox>
</object>
</annotation>
